crunch_encrypt/__init__.py
crunch_encrypt/__main__.py
crunch_encrypt/__version__.py
crunch_encrypt/_base.py
crunch_encrypt/cli.py
crunch_encrypt/ecies/__init__.py
crunch_encrypt/ecies/_constants.py
crunch_encrypt/ecies/_helpers.py
crunch_encrypt/ecies/_io.py
crunch_encrypt/ecies/_types.py
crunch_encrypt-0.1.0.dist-info/METADATA
crunch_encrypt-0.1.0.dist-info/WHEEL
crunch_encrypt-0.1.0.dist-info/entry_points.txt
crunch_encrypt-0.1.0.dist-info/top_level.txt
crunch_encrypt-0.1.0.dist-info/RECORD
