Metadata-Version: 2.1
Name: crunch-encrypt
Version: 0.1.0
Summary: crunch-encrypt - Encryption module for the CrunchDAO Platform
Home-page: https://github.com/crunchdao/crunch-encrypt
Author: Enzo CACERES
Author-email: enzo.caceres@crunchdao.com
Keywords: package development template
Classifier: Intended Audience :: Developers
Classifier: Programming Language :: Python :: 3.7
Requires-Python: >=3
Requires-Dist: click
Requires-Dist: cryptography
Requires-Dist: requests
Provides-Extra: test
Requires-Dist: parameterized ; extra == 'test'
Requires-Dist: pytest ; extra == 'test'
Requires-Dist: pytest-cov ; extra == 'test'
Requires-Dist: lorem-text ; extra == 'test'
